networker/__init__.py
networker/console.py
networker/diamond.py
networker/io.py
networker/main.py
networker/network.py
networker/parser.py
networker/plot.py
networker-0.2.3.dist-info/METADATA
networker-0.2.3.dist-info/RECORD
networker-0.2.3.dist-info/WHEEL
networker-0.2.3.dist-info/entry_points.txt
networker-0.2.3.dist-info/top_level.txt
