Metadata-Version: 2.1
Name: networker
Version: 0.2.3
Summary: a python package to generate and analyse protein similarity networks
Home-page: https://github.com/DrBoothTJ/networker
Author: Thomas J. Booth
Author-email: thoboo@biosustain.dtu.dk
License: GNU General Public License v3.0
Platform: UNKNOWN
Requires-Python: >=3.7
Requires-Dist: numpy
Requires-Dist: pandas
Requires-Dist: plotly
Requires-Dist: pyvis
